llm_token_tracker/__init__.py
llm_token_tracker/wrapper.py
llm_token_tracker-0.4.0.dist-info/licenses/LICENSE
llm_token_tracker-0.4.0.dist-info/METADATA
llm_token_tracker-0.4.0.dist-info/WHEEL
llm_token_tracker-0.4.0.dist-info/top_level.txt
llm_token_tracker-0.4.0.dist-info/RECORD
