Metadata-Version: 2.4
Name: llm-token-tracker
Version: 0.4.0
Summary: A package to track LLM token usage in context
Author: Laurin
License-Expression: MIT
Keywords: llm,token,tracker,xai,grok
Classifier: Development Status :: 3 - Alpha
Classifier: Intended Audience :: Developers
Classifier: Programming Language :: Python :: 3.13
Classifier: Topic :: Software Development :: Libraries :: Python Modules
Requires-Python: >=3.13
License-File: LICENSE
Requires-Dist: xai-sdk
Dynamic: license-file
